PySpice/__init__.py
PySpice/Config/ConfigInstall.py
PySpice/Config/__init__.py
PySpice/Config/logging.yml
PySpice/DeviceLibrary/__init__.py
PySpice/Doc/ExampleTools.py
PySpice/Doc/__init__.py
PySpice/Logging/Logging.py
PySpice/Logging/__init__.py
PySpice/Math/Calculus.py
PySpice/Math/__init__.py
PySpice/Physics/MaterialProperties.py
PySpice/Physics/PhysicalConstants.py
PySpice/Physics/Resistor.py
PySpice/Physics/SemiConductor.py
PySpice/Physics/__init__.py
PySpice/Plot/BodeDiagram.py
PySpice/Plot/__init__.py
PySpice/Probe/Plot.py
PySpice/Probe/WaveForm.py
PySpice/Probe/__init__.py
PySpice/Scripts/__init__.py
PySpice/Scripts/cir2py.py
PySpice/Scripts/pyspice_post_installation.py
PySpice/Spice/BasicElement.py
PySpice/Spice/ElementParameter.py
PySpice/Spice/HighLevelElement.py
PySpice/Spice/Library.py
PySpice/Spice/Netlist.py
PySpice/Spice/Parser.py
PySpice/Spice/RawFile.py
PySpice/Spice/Simulation.py
PySpice/Spice/__init__.py
PySpice/Spice/Expression/Ast.py
PySpice/Spice/Expression/Parser.py
PySpice/Spice/Expression/__init__.py
PySpice/Spice/Expression/parsetab.py
PySpice/Spice/NgSpice/RawFile.py
PySpice/Spice/NgSpice/Server.py
PySpice/Spice/NgSpice/Shared.py
PySpice/Spice/NgSpice/Simulation.py
PySpice/Spice/NgSpice/SimulationType.py
PySpice/Spice/NgSpice/__init__.py
PySpice/Spice/NgSpice/api.h
PySpice/Spice/Xyce/RawFile.py
PySpice/Spice/Xyce/Server.py
PySpice/Spice/Xyce/Simulation.py
PySpice/Spice/Xyce/__init__.py
PySpice/Tools/EnumFactory.py
PySpice/Tools/File.py
PySpice/Tools/Path.py
PySpice/Tools/StringTools.py
PySpice/Tools/__init__.py
PySpice/Unit/SiUnits.py
PySpice/Unit/Unit.py
PySpice/Unit/__init__.py
tasks/SECRET_CONFIG.py
tasks/__init__.py
tasks/anaconda.py
tasks/clean.py
tasks/doc.py
tasks/git.py
tasks/ngspice.py
tasks/release.py
tasks/test.py
PySpice-1.4.3.dist-info/LICENSE.txt
PySpice-1.4.3.dist-info/METADATA
PySpice-1.4.3.dist-info/WHEEL
PySpice-1.4.3.dist-info/entry_points.txt
PySpice-1.4.3.dist-info/top_level.txt
PySpice-1.4.3.dist-info/RECORD
