Metadata-Version: 2.1
Name: PySpice
Version: 1.4.3
Summary: Simulate electronic circuit using Python and the Ngspice / Xyce simulators
Home-page: https://github.com/FabriceSalvaire/PySpice
Author: Fabrice Salvaire
Author-email: pyspice@fabrice-salvaire.fr
Maintainer: Fabrice Salvaire
Maintainer-email: pyspice@fabrice-salvaire.fr
License: GPLv3
Project-URL: Documentation, https://pyspice.fabrice-salvaire.fr
Project-URL: Code, https://github.com/FabriceSalvaire/PySpice
Project-URL: Issue Tracker, https://github.com/FabriceSalvaire/PySpice/issues
Project-URL: Forum, https://pyspice.discourse.group
Keywords: ngspice,xyce,spice,berkeley,electronic,circuit,simulation,simulator
Platform: any
Classifier: Topic :: Scientific/Engineering
Classifier: Intended Audience :: Education
Classifier: Development Status :: 5 - Production/Stable
Classifier: License :: OSI Approved :: GNU General Public License (GPL)
Classifier: Operating System :: OS Independent
Classifier: Programming Language :: Python :: 3.6
Requires-Python: >=3.6
Requires-Dist: PyYAML (>=5.3)
Requires-Dist: cffi (>=1.14)
Requires-Dist: matplotlib (>=3.2)
Requires-Dist: numpy (>=1.18)
Requires-Dist: ply (>=3.11)
Requires-Dist: scipy (>=1.4)
Requires-Dist: requests (>=2.23)
